piter/__init__.py
piter/cli/__init__.py
piter/cli/app.py
piter/cli/output.py
piter/cli/utils.py
piter/config/__init__.py
piter/config/default.py
piter/config/models.py
piter/config/utils.py
piter/env/__init__.py
piter/env/env.py
piter-0.8.0.dist-info/METADATA
piter-0.8.0.dist-info/WHEEL
piter-0.8.0.dist-info/entry_points.txt
piter-0.8.0.dist-info/top_level.txt
piter-0.8.0.dist-info/RECORD
