Metadata-Version: 2.1
Name: piter
Version: 0.8.0
Home-page: https://github.com/mishankov/piter
Author: Denis Mishankov
Author-email: mishankov@mail.com
Classifier: Programming Language :: Python :: 3.7
Classifier: Programming Language :: Python :: 3.8
Classifier: Programming Language :: Python :: 3.9
Classifier: Programming Language :: Python :: 3.10
Classifier: License :: OSI Approved :: MIT License
Classifier: Operating System :: OS Independent
Requires-Python: >=3.7
Requires-Dist: typer
Requires-Dist: toml
Requires-Dist: colorama
